{
  "metadata": {
    "scraped_at": "2025-09-10T21:05:18.207373",
    "total_questions": 3,
    "successful_scrapes": 3,
    "total_duration": 36.581134,
    "platform_stats": {
      "geeksforgeeks": {
        "success": 3,
        "failed": 0
      },
      "codingninjas": {
        "success": 3,
        "failed": 0
      }
    }
  },
  "questions": [
    {
      "question_id": "srinpttpt",
      "success": true,
      "platforms_scraped": [
        "geeksforgeeks",
        "codingninjas"
      ],
      "content": {
        "geeksforgeeks": {
          "platform": "geeksforgeeks",
          "url": "https://practice.geeksforgeeks.org/problems/search-query-auto-complete/0",
          "title": "Title not found",
          "problem_statement": "Problem statement not found",
          "difficulty": "hard",
          "tags": [],
          "topics": [],
          "constraints": [],
          "test_cases": [],
          "examples": [],
          "code_templates": {},
          "hints": [],
          "editorial_url": null,
          "discussion_count": null,
          "likes": null,
          "dislikes": null,
          "scraped_at": "2025-09-10 21:05:18.143145",
          "scraping_duration": 35.53865194320679,
          "scraping_success": true,
          "error_message": null
        },
        "codingninjas": {
          "platform": "codingninjas",
          "url": "https://www.codingninjas.com/studio/problems/find-character-case_58513",
          "title": "Title not found",
          "problem_statement": "Problem statement not found",
          "difficulty": "unknown",
          "tags": [],
          "topics": [],
          "constraints": [],
          "test_cases": [],
          "examples": [],
          "code_templates": {},
          "hints": [],
          "editorial_url": null,
          "discussion_count": null,
          "likes": null,
          "dislikes": null,
          "scraped_at": "2025-09-10 21:05:14.921445",
          "scraping_duration": 32.27769207954407,
          "scraping_success": true,
          "error_message": "name 'url' is not defined"
        }
      },
      "errors": {},
      "total_duration": 35.54607701301575,
      "scraped_at": "2025-09-10T21:04:42.655159"
    },
    {
      "question_id": "dttyps",
      "success": true,
      "platforms_scraped": [
        "geeksforgeeks",
        "codingninjas"
      ],
      "content": {
        "geeksforgeeks": {
          "platform": "geeksforgeeks",
          "url": "https://www.geeksforgeeks.org/problems/data-type-1666706751/1",
          "title": "Oops!! Something went wrong.",
          "problem_statement": "Problem statement not found",
          "difficulty": "unknown",
          "tags": [],
          "topics": [],
          "constraints": [],
          "test_cases": [],
          "examples": [],
          "code_templates": {},
          "hints": [],
          "editorial_url": null,
          "discussion_count": null,
          "likes": null,
          "dislikes": null,
          "scraped_at": "2025-09-10 21:05:18.126027",
          "scraping_duration": 35.53963375091553,
          "scraping_success": true,
          "error_message": null
        },
        "codingninjas": {
          "platform": "codingninjas",
          "url": "https://www.codingninjas.com/studio/problems/data-type_8357232",
          "title": "Title not found",
          "problem_statement": "Problem statement not found",
          "difficulty": "unknown",
          "tags": [],
          "topics": [],
          "constraints": [],
          "test_cases": [],
          "examples": [],
          "code_templates": {},
          "hints": [],
          "editorial_url": null,
          "discussion_count": null,
          "likes": null,
          "dislikes": null,
          "scraped_at": "2025-09-10 21:05:14.954238",
          "scraping_duration": 32.31021595001221,
          "scraping_success": true,
          "error_message": "name 'url' is not defined"
        }
      },
      "errors": {},
      "total_duration": 35.55102205276489,
      "scraped_at": "2025-09-10T21:04:42.655187"
    },
    {
      "question_id": "iflssttmnts",
      "success": true,
      "platforms_scraped": [
        "geeksforgeeks",
        "codingninjas"
      ],
      "content": {
        "geeksforgeeks": {
          "platform": "geeksforgeeks",
          "url": "https://practice.geeksforgeeks.org/problems/java-if-else-decision-making0924/0",
          "title": "Title not found",
          "problem_statement": "Problem statement not found",
          "difficulty": "unknown",
          "tags": [],
          "topics": [],
          "constraints": [],
          "test_cases": [],
          "examples": [],
          "code_templates": {},
          "hints": [],
          "editorial_url": null,
          "discussion_count": null,
          "likes": null,
          "dislikes": null,
          "scraped_at": "2025-09-10 21:05:18.135916",
          "scraping_duration": 35.534937143325806,
          "scraping_success": true,
          "error_message": null
        },
        "codingninjas": {
          "platform": "codingninjas",
          "url": "https://www.codingninjas.com/studio/problems/if-else-decision-making_8357235",
          "title": "Title not found",
          "problem_statement": "Problem statement not found",
          "difficulty": "unknown",
          "tags": [],
          "topics": [],
          "constraints": [],
          "test_cases": [],
          "examples": [],
          "code_templates": {},
          "hints": [],
          "editorial_url": null,
          "discussion_count": null,
          "likes": null,
          "dislikes": null,
          "scraped_at": "2025-09-10 21:05:14.877745",
          "scraping_duration": 32.23895978927612,
          "scraping_success": true,
          "error_message": "name 'url' is not defined"
        }
      },
      "errors": {},
      "total_duration": 35.543590784072876,
      "scraped_at": "2025-09-10T21:04:42.655204"
    }
  ]
}